{
  "poet": {
    "name_ar": "صيفي الأسلت",
    "name_en": "Ṣayfī al-Aslat",
    "tribe": "Aws",
    "region": "Hijaz",
    "chronological_layer": "mukhaḍramūn",
    "gender": "male",
    "number_of_lines": 150,
    "metadata_notes": ""
  },
  "poems": [
    {
      "poem_index": 0,
      "poem_id": "ṣayfī_al-aslat_000",
      "meter": "وافر",
      "verses": [
        {
          "verse_index": 0,
          "text": "لأكناف الجريب فنعف سلمى  فأحساء الأساحلِ فالجنابُ"
        },
        {
          "verse_index": 1,
          "text": "إلى روضات ليلى مخصباتٍ  عوافٍ قد أصات بها الذباب"
        },
        {
          "verse_index": 2,
          "text": "كأنَّ المكر والحوذانَ فيها  وحماض التلاعِ الكهلَ غاب"
        },
        {
          "verse_index": 3,
          "text": "أحق شبابكم من حرب قوم  له خلق وناحية وداب"
        },
        {
          "verse_index": 4,
          "text": "وإن تابوا فإن بني سليم  وإخوتهم هوازن قد أنابوا"
        },
        {
          "verse_index": 5,
          "text": "لأعداد المياه ليحضروها  وبالحولان كلب والرباب"
        },
        {
          "verse_index": 6,
          "text": "وأسفل منكم بكر حلول  على تعثاى رئيت القباب"
        }
      ]
    },
    {
      "poem_index": 1,
      "poem_id": "ṣayfī_al-aslat_001",
      "meter": "طويل",
      "verses": [
        {
          "verse_index": 0,
          "text": "أيا راكباً إما عرضت فبلغن  مغلغلة عنى لؤى بن غالب"
        },
        {
          "verse_index": 1,
          "text": "رسول امرئ قد راعه ذات بينكم  على النأي محزونٍ بذلك ناصب"
        },
        {
          "verse_index": 2,
          "text": "وقد كان عندي للهموم معرس  فلم أقض منها حاجتي ومآربي"
        },
        {
          "verse_index": 3,
          "text": "ونبئتكم شرجين كل قبيلة  لها أزمل من بين مُدكٍ وحاطب"
        },
        {
          "verse_index": 4,
          "text": "أعيذكم بالله من شر صنعكم  وشر تباغيكم ودس العقارب"
        },
        {
          "verse_index": 5,
          "text": "وإظهارِ أخلاقٍ ونجوى سقيمةٍ  كوخز الأشافي وقعها حق صائبر"
        },
        {
          "verse_index": 6,
          "text": "فذكرهم باللَه أولَ وهلة  وإحلال أحرام الظباء الشوازب"
        },
        {
          "verse_index": 7,
          "text": "وقل لهم واللَه يحكم حكمه  ذروا الحرب تذهب عنكم في المراحب"
        },
        {
          "verse_index": 8,
          "text": "متى تبعثوها تبعثوها ذميمةً  هي الغُول للأقصين أو للأقارب"
        },
        {
          "verse_index": 9,
          "text": "تقطع أرحاماً وتهلك أمةً  وتبرى السديف من سنام وغارب"
        },
        {
          "verse_index": 10,
          "text": "وتستبدلوا بالأتحمية  شليلاً وأصداء ثياب المحارب"
        },
        {
          "verse_index": 11,
          "text": "وبالمسك والكافور غُبراً سوابغاً  كأن قتيريها عيون الجنادب"
        },
        {
          "verse_index": 12,
          "text": "فإياكم والحرب لا تعلقنكم  وحوضاً وخيم الماء مرَّ المشارب"
        },
        {
          "verse_index": 13,
          "text": "تزين للأقوام ثم يرونها  بعاقبة إذ بينت أم صاحب"
        },
        {
          "verse_index": 14,
          "text": "تحرق لا تشوى ضعيفاً وتنتحي  ذوي العز منكم بالحتوف الصوائب"
        },
        {
          "verse_index": 15,
          "text": "ألم تعلموا ما كان في حرب داحس  فتعتبروا أو كان في حرب حاطب"
        },
        {
          "verse_index": 16,
          "text": "وكم قد أصابت من شريف مسودٍ  طويل العماد ضيفه غير خائب"
        },
        {
          "verse_index": 17,
          "text": "عظيم رماد النار يُحمد أمرُه  وذي شيمة محضٍ كريم المضارب"
        },
        {
          "verse_index": 18,
          "text": "وماءٍ هريق في الضلال كأنما  أذاعت به ريح الصبا والجنائب"
        },
        {
          "verse_index": 19,
          "text": "يخبركم عنها امرؤٌ حقُّ عالم  بأيامها واللم علمُ التجارب"
        },
        {
          "verse_index": 20,
          "text": "فبيعوا الحراب ملمحارب واذكروا  حسابكم واللَه خير محاسب"
        },
        {
          "verse_index": 21,
          "text": "ولى مرئ افاختار ديناً فلا يكن  عليكم رقيباً غيرَ رب الثواقب"
        },
        {
          "verse_index": 22,
          "text": "أقيموا لنا ديناً حنيفاً فانتم  لنا غاية قد يُهتدى بالذوائب"
        },
        {
          "verse_index": 23,
          "text": "وأنتم لهذا الناس نور وعصمة  تؤمون والأحلام غير عوازب"
        },
        {
          "verse_index": 24,
          "text": "وأنتم إذا ما حصل الناس جوهر  لكم سُرة البطحاء شُمَّ الأرانب"
        },
        {
          "verse_index": 25,
          "text": "تصونون أجساداً كراماً عتيقة  مهذبة الأنساب غير أشائب"
        },
        {
          "verse_index": 26,
          "text": "ترى طالب الحاجات نحو بيوتكم  عصائب هلكى تهتدى بعصائب"
        },
        {
          "verse_index": 27,
          "text": "لقد علم الأقوام أن سراتك  على كل حالٍ خيرُ أهل الجباجب"
        },
        {
          "verse_index": 28,
          "text": "وأفضله رأياً وأعلاه سنة  وأقوله للحق وسط المواكب"
        },
        {
          "verse_index": 29,
          "text": "فقوموا فصلوا لربكم وتمسحوا  بأركان هذا البيت بين الأخاشب"
        },
        {
          "verse_index": 30,
          "text": "فعندكم منه بلاء مصدق  غداة أبي يكسوم هادي الكتائب"
        },
        {
          "verse_index": 31,
          "text": "كتيبته بالسهل تمسى ورحله  على القاذفات في رؤوس المناقب"
        },
        {
          "verse_index": 32,
          "text": "فلما أتاكم نصر ذي العرش ردهم  جنود المليك بين ساف وحاصب"
        },
        {
          "verse_index": 33,
          "text": "فولوا سراعاً هاربين ولم يؤب  إلى أهله ملحبش غيرُ عصائب"
        },
        {
          "verse_index": 34,
          "text": "فإن تهلكوا نهلك وتهلك مواسم  يعاش بها قول امرئٍ غير كاذب"
        }
      ]
    },
    {
      "poem_index": 2,
      "poem_id": "ṣayfī_al-aslat_002",
      "meter": "بسيط",
      "verses": [
        {
          "verse_index": 0,
          "text": "لقد رأيت بني عمرو فما وهنوا  عند اللقاء وما هموا بتكذيب"
        },
        {
          "verse_index": 1,
          "text": "ألا فدى لهم أمي وما ولدت  غداة يمشون إرقال المصاعيب"
        },
        {
          "verse_index": 2,
          "text": "بكل سلهبةٍ كالأيمِ ماضية  وكل أبيضَ ماضي الحدِّ مخشوب"
        }
      ]
    },
    {
      "poem_index": 3,
      "poem_id": "ṣayfī_al-aslat_003",
      "meter": "وافر",
      "verses": [
        {
          "verse_index": 0,
          "text": "أسرت مخلداً فعفوت عنه  وعند اللَه صالح ما أنيت"
        },
        {
          "verse_index": 1,
          "text": "مزينة عنده ويهود قررى  وقومي كل ذلكم كفيت"
        }
      ]
    },
    {
      "poem_index": 4,
      "poem_id": "ṣayfī_al-aslat_004",
      "meter": "وافر",
      "verses": [
        {
          "verse_index": 0,
          "text": "فمن ورِث الغنى فليصطنعه  صنيعته ويجهد كل جهدِ"
        },
        {
          "verse_index": 1,
          "text": "ولا يمنعه من حمدِ وشكر  ولا يبخل به عن فعل رُشد"
        }
      ]
    },
    {
      "poem_index": 5,
      "poem_id": "ṣayfī_al-aslat_005",
      "meter": "طويل",
      "verses": [
        {
          "verse_index": 0,
          "text": "رقود الضحى صفرُ الحشى منتهى المُنى  قطوفُ الخُطى تمشي الهوينا فتبهرُ"
        },
        {
          "verse_index": 1,
          "text": "خفيضة أعلى الصوت ليست بسلفع  ولا نمةٍ خراجة حين تظهر"
        },
        {
          "verse_index": 2,
          "text": "ويكرمنها جاراتها فيزرنها  وتعتل عن إنيانهن فتعذَر"
        },
        {
          "verse_index": 3,
          "text": "وليس بها أن تستهين بجارة  ولكنها من ذاك تحيا وتحصر"
        },
        {
          "verse_index": 4,
          "text": "وإن هي لم تقصد لهُن أتينها  نواعِمَ بيضاً مشيهن التأطر"
        }
      ]
    },
    {
      "poem_index": 6,
      "poem_id": "ṣayfī_al-aslat_006",
      "meter": "طويل",
      "verses": [
        {
          "verse_index": 0,
          "text": "وقد لاح في الصبح الثريا كما ترى  كعنقود ملاحيةٍ حين نورا"
        }
      ]
    },
    {
      "poem_index": 7,
      "poem_id": "ṣayfī_al-aslat_007",
      "meter": "بحر مجزوء الكامل",
      "verses": [
        {
          "verse_index": 0,
          "text": "أبلغ أبا حصن وبع  ض القول عندي ذو كباره"
        },
        {
          "verse_index": 1,
          "text": "أن ابن أم المرء لي  س من الحديد ولا الحجاره"
        },
        {
          "verse_index": 2,
          "text": "ماذا عليكم أن يك  ون لكم بها رحلا عماره"
        },
        {
          "verse_index": 3,
          "text": "يحمى ذماركم وبع  وبعض القوم لا يحمي ذماره"
        },
        {
          "verse_index": 4,
          "text": "يبنى لكم خيراً وبن  يان الكريم له أثاره"
        }
      ]
    },
    {
      "poem_index": 8,
      "poem_id": "ṣayfī_al-aslat_008",
      "meter": "بسيط",
      "verses": [
        {
          "verse_index": 0,
          "text": "من يصل نارى بلا ذنبٍ ولا ترةٍ  يصل بنار كريم غير غدار"
        },
        {
          "verse_index": 1,
          "text": "أنا النذير لكم متى مجاهرةً  كي لا ألام على نهي وإنذار"
        },
        {
          "verse_index": 2,
          "text": "فإن عصيتم مقالي اليوم فاعترفوا  أن سوف تلقون خزياً ظاهر العار"
        },
        {
          "verse_index": 3,
          "text": "لترحض أحاديثاً ملعنة  لهو المقيم ولهو المدلج الساري"
        },
        {
          "verse_index": 4,
          "text": "من كان في نفسه حوجا يطلبها  عندي فإني له رهن بإصحار"
        },
        {
          "verse_index": 5,
          "text": "أقيم عوجته إن كان ذا عوج  كما يقوم قدح النبعة الباري"
        },
        {
          "verse_index": 6,
          "text": "وصاحب الوتر ليس الدهرَ مدركه  عندي وإني لدراك بأوتار"
        }
      ]
    },
    {
      "poem_index": 9,
      "poem_id": "ṣayfī_al-aslat_009",
      "meter": "وافر",
      "verses": [
        {
          "verse_index": 0,
          "text": "فلست لحاصن إن لم ترونا  نجالدكم كأنا شرب خمر"
        },
        {
          "verse_index": 1,
          "text": "ملكنا الناس قد علمت معدٌّ  فلم تغلب ولم تسبقُ بوِتر"
        },
        {
          "verse_index": 2,
          "text": "هممنا بالإقامة ثم سرنا  بسير حذيفة الخير ابن بدر"
        }
      ]
    },
    {
      "poem_index": 10,
      "poem_id": "ṣayfī_al-aslat_010",
      "meter": "وافر",
      "verses": [
        {
          "verse_index": 0,
          "text": "أقيسٌ إن هلكتُ وأنت حيٌّ  فلا تعدم مواصلة الفقير"
        }
      ]
    },
    {
      "poem_index": 11,
      "poem_id": "ṣayfī_al-aslat_011",
      "meter": "سريع",
      "verses": [
        {
          "verse_index": 0,
          "text": "قالت ولم تقصد لقيل الخنا  مهلاً فقد أبلغت أسماعي"
        },
        {
          "verse_index": 1,
          "text": "أنكرته حين توسمته  والحرب غعول ذات أوجاع"
        },
        {
          "verse_index": 2,
          "text": "من يدق الحرب يجد طعمها  مراً وتحبسه بجعجاع"
        },
        {
          "verse_index": 3,
          "text": "قد خصت البيضة رأسي فما  أطعم غمضاً غير تهجاع"
        },
        {
          "verse_index": 4,
          "text": "أسعى على جل بني مالك  كل امرئ في شأنه ساعي"
        },
        {
          "verse_index": 5,
          "text": "أعددت للأعداء موضوته  فضفاضة كالنهى بالقاع"
        },
        {
          "verse_index": 6,
          "text": "أحفزها عني بذي رونقٍ  مهند كالملح قطاع"
        },
        {
          "verse_index": 7,
          "text": "صدق حسام وادقٍ حده  ومجنإ أسمر قراع"
        },
        {
          "verse_index": 8,
          "text": "بز امرئ مستبسل حاذر  للدهر جلدٍ غير مجزاع"
        },
        {
          "verse_index": 9,
          "text": "الحزم والقوة خير من ال  إدهان والفكة والهاع"
        },
        {
          "verse_index": 10,
          "text": "ليس قطاً مثل قطى ولا ال  مرعى في الأقوام كالراعي"
        },
        {
          "verse_index": 11,
          "text": "لا نألم القتل ونجزى به ال  أعداء كيل الصاع بالصاع"
        },
        {
          "verse_index": 12,
          "text": "نذودهم عنا بمستنةٍ  ذات عرانين ودفاع"
        },
        {
          "verse_index": 13,
          "text": "كأنهم أسد لدى أشبلِ  ينهتن في غيل وأجزاع"
        },
        {
          "verse_index": 14,
          "text": "حتى تجلت ولنا غاية  من بين جمعٍ غير جماع"
        },
        {
          "verse_index": 15,
          "text": "هلا سألت الخيل إذ قلصت  ما كان إبطائي وإسراعي"
        },
        {
          "verse_index": 16,
          "text": "هل أبذلُ المال على حبه  فيهم وآتي دعوة الداعي"
        },
        {
          "verse_index": 17,
          "text": "وأضربُ القونس يوم الوغى  بالسيف لم يقصر به باعي"
        },
        {
          "verse_index": 18,
          "text": "وأقطع الخرق يخافُ الردى  فيه على أدماء هلواع"
        },
        {
          "verse_index": 19,
          "text": "ذات أهاسيج جمالية  حشت بجاري وأقطاع"
        },
        {
          "verse_index": 20,
          "text": "تعطى على الأين وتنجو من الض  رب أمونٍ غير مظلاع"
        },
        {
          "verse_index": 21,
          "text": "كأن أطرافَ ولياتها  في شمألٍ حصا زعزاع"
        },
        {
          "verse_index": 22,
          "text": "أزين الرحل بمعقومة  حاريةٍ أو ذات أقطاع"
        },
        {
          "verse_index": 23,
          "text": "أقضى بها الحاجات إن الفتى  رهنٌ بذي لونين خدّاع"
        }
      ]
    },
    {
      "poem_index": 12,
      "poem_id": "ṣayfī_al-aslat_012",
      "meter": "سريع",
      "verses": [
        {
          "verse_index": 0,
          "text": "إذا جمادى منعت قطرها  زان جنابي عطن معصف"
        }
      ]
    },
    {
      "poem_index": 13,
      "poem_id": "ṣayfī_al-aslat_013",
      "meter": "منسرح",
      "verses": [
        {
          "verse_index": 0,
          "text": "نحن بما عندنا وأنت بما  عندك راض والرأي مشترك"
        }
      ]
    },
    {
      "poem_index": 14,
      "poem_id": "ṣayfī_al-aslat_014",
      "meter": "طويل",
      "verses": [
        {
          "verse_index": 0,
          "text": "يقول أبو قيس وأصبح غادياً  ألا ما استطعتم من وصاتي فافعلوا"
        },
        {
          "verse_index": 1,
          "text": "فأوصيكم بالله والبر والتقى  وأعراضكم والبر باللَه أول"
        },
        {
          "verse_index": 2,
          "text": "وإن قومكم سادوا فلا تحسدنهم  وإن كنتم أهل الرياسة فاعدلوا"
        },
        {
          "verse_index": 3,
          "text": "وإن نزلت إحدى الدواهي بقومكم  فأنفكم دون العشيرة فاجعلوا"
        },
        {
          "verse_index": 4,
          "text": "وإن ناب عرمٌ فادحٌ فارففوهم  وما خملوكم في الملمات فاحملوا"
        },
        {
          "verse_index": 5,
          "text": "وأن أنتم أمعرتم فتعففوا  وإن كان فضل الخير فيكم فأفضلوا"
        }
      ]
    },
    {
      "poem_index": 15,
      "poem_id": "ṣayfī_al-aslat_015",
      "meter": "بسيط",
      "verses": [
        {
          "verse_index": 0,
          "text": "ثم ارعويت وقد طال الوقوف بنا  فيها فصرتُ إلى وجناء شملال"
        },
        {
          "verse_index": 1,
          "text": "تعطيك مشياً وإرقالاً ودأدأة  إذا تسربلت الآكام بالآل"
        },
        {
          "verse_index": 2,
          "text": "تردى الأكام إذا صرت جنادبها  منها بصُلبٍ وقاح البطنِ عَمال"
        },
        {
          "verse_index": 3,
          "text": "لم يمنع الشرب منها غير أن نطقت  حمامة في غصون ذاتِ أوقال"
        }
      ]
    },
    {
      "poem_index": 16,
      "poem_id": "ṣayfī_al-aslat_016",
      "meter": "خفيف",
      "verses": [
        {
          "verse_index": 0,
          "text": "سبحوا اللَه شرق كل صباح  طلعت شمسه وكل هلال"
        },
        {
          "verse_index": 1,
          "text": "عالم السرِّ والبيان لدينا  ليس ما قال ربنا بضلال"
        },
        {
          "verse_index": 2,
          "text": "وله الطير تستريد وتأوى  في وُكور من آمنات الجبال"
        },
        {
          "verse_index": 3,
          "text": "وله الوحش بالفلاة تراها  في حقاف وفي ظلال الرمال"
        },
        {
          "verse_index": 4,
          "text": "وله هودت يهود ودانت  كل دين إذا ذكرت عضال"
        },
        {
          "verse_index": 5,
          "text": "وله شمس النصارى وقاموا  كل عيد لربهم واحتفال"
        },
        {
          "verse_index": 6,
          "text": "وله الراهب الجيس تراه  رهن بؤسٍ وكان تاعم بال"
        },
        {
          "verse_index": 7,
          "text": "يا بني الأرحام لا تقطعوها  وصلوها قصيرة من طوال"
        },
        {
          "verse_index": 8,
          "text": "واتقوا اللَه في ضعاف اليتامى  ربما يستحل غير الحلال"
        },
        {
          "verse_index": 9,
          "text": "واعلموا أن اليتيم وليا  عالماً يهتدى بغير السؤال"
        },
        {
          "verse_index": 10,
          "text": "ثم مال اليتيم لا تأكلوه  إن مال اليتيم يرعاه والى"
        },
        {
          "verse_index": 11,
          "text": "يا بني التخوم لا تخزلوها  إن خزل التخوم ذو عقال"
        },
        {
          "verse_index": 12,
          "text": "يا بني الأيام لا تأمنوها  واحذروا مكرها ومر الليالي"
        },
        {
          "verse_index": 13,
          "text": "واعلموا أن مرها لنفاد ال  خلق ما كان من جديد وبالي"
        },
        {
          "verse_index": 14,
          "text": "واجمعوا أمركم على البر والتق  وى وترك الخفا وأخذ الحلال"
        }
      ]
    },
    {
      "poem_index": 17,
      "poem_id": "ṣayfī_al-aslat_017",
      "meter": "وافر",
      "verses": [
        {
          "verse_index": 0,
          "text": "أرب الناس أشياء ألمت  يلف الصعب منها بالذلول"
        },
        {
          "verse_index": 1,
          "text": "أرب الناس أما إذ ضللنا  فيسرنا لمعروف السبيل"
        },
        {
          "verse_index": 2,
          "text": "فلولا ربنا كنا يهودا  وما دين اليهود بذي شكول"
        },
        {
          "verse_index": 3,
          "text": "ولولا ربنا كنا نصارى  مع الرهبان في جبل الجليل"
        },
        {
          "verse_index": 4,
          "text": "ولكنا خلقنا إذ خلقنا  حنيفاً ديننا عن كل جيل"
        },
        {
          "verse_index": 5,
          "text": "نسوف الهدى ترسف مذعناتٍ  مكشفة المناكب في الجلول"
        }
      ]
    },
    {
      "poem_index": 18,
      "poem_id": "ṣayfī_al-aslat_018",
      "meter": "رمل",
      "verses": [
        {
          "verse_index": 0,
          "text": "رجموا بالغيب كيما يعلموا  من عديد القوم ما لا يعلم"
        }
      ]
    },
    {
      "poem_index": 19,
      "poem_id": "ṣayfī_al-aslat_019",
      "meter": "وافر",
      "verses": [
        {
          "verse_index": 0,
          "text": "بنى متى هلكت وأنت حيٌّ  فلا تحرم فواضلك العديما"
        },
        {
          "verse_index": 1,
          "text": "ومالك فاصطنعه واصلحنه  تجد فيه الفواضل والنعيما"
        }
      ]
    },
    {
      "poem_index": 20,
      "poem_id": "ṣayfī_al-aslat_020",
      "meter": "وافر",
      "verses": [
        {
          "verse_index": 0,
          "text": "وكان أبو أحيحة قد علمتم  بمكة غير مهتضم ذميم"
        },
        {
          "verse_index": 1,
          "text": "إذا شد العصابة ذات يوم  وقام إلى المجالس والخصوم"
        },
        {
          "verse_index": 2,
          "text": "فقد حرمت على من كان يمشي  بمكة غير مدخل سقيم"
        },
        {
          "verse_index": 3,
          "text": "وكان البختري غداة جمع  يدافعهم بلقمان الحكيم"
        },
        {
          "verse_index": 4,
          "text": "بأزهر من سُراة بني أؤى  كبدر الليل راق على النجوم"
        },
        {
          "verse_index": 5,
          "text": "هو البيت الذي بنيت عليه  قريش السر في الزمن القديم"
        },
        {
          "verse_index": 6,
          "text": "وسطت ذوائب الفرعين منها  فأنت لباب سرهم الصميم"
        }
      ]
    },
    {
      "poem_index": 21,
      "poem_id": "ṣayfī_al-aslat_021",
      "meter": "متقارب",
      "verses": [
        {
          "verse_index": 0,
          "text": "ومن صنعه يومَ فيل الحبو  ش إذ كلما بعثوه رزم"
        },
        {
          "verse_index": 1,
          "text": "محاجنهم تحت أقرابه  وقد شرموا أنفه فانحزم"
        },
        {
          "verse_index": 2,
          "text": "وقد جعلوا سوطه مغولاً  إذا يمموه قفاه كلم"
        },
        {
          "verse_index": 3,
          "text": "فولى وأدبر أدراجه  وقد باء بالظلم من كان ثم"
        },
        {
          "verse_index": 4,
          "text": "فأرسل من فوقهم حاصباً  فلفهم مثل لف القزم"
        },
        {
          "verse_index": 5,
          "text": "تحض على الصبر أحبارهم  وقد ثأجوا كثؤاج الغنم"
        }
      ]
    },
    {
      "poem_index": 22,
      "poem_id": "ṣayfī_al-aslat_022",
      "meter": "وافر",
      "verses": [
        {
          "verse_index": 0,
          "text": "ألا من مبلغٌ حسان عني  أطبٌّ كان داؤك أم جنونُ"
        }
      ]
    },
    {
      "poem_index": 23,
      "poem_id": "ṣayfī_al-aslat_023",
      "meter": "وافر",
      "verses": [
        {
          "verse_index": 0,
          "text": "وأحرزنا المغانم واسقبحنا  حمى الأعداء واللَه المعين"
        },
        {
          "verse_index": 1,
          "text": "بغير خلابة مكر ولكن  مجاهرة ولم يخبأ كمين"
        }
      ]
    },
    {
      "poem_index": 24,
      "poem_id": "ṣayfī_al-aslat_024",
      "meter": "وافر",
      "verses": [
        {
          "verse_index": 0,
          "text": "على أن قد فجعت بذي حفاظٍ  فعاودني له حزنٌ رصين"
        },
        {
          "verse_index": 1,
          "text": "فإما تقتلوه فإن عمروا  أعض برأسه عضب سنين"
        }
      ]
    },
    {
      "poem_index": 25,
      "poem_id": "ṣayfī_al-aslat_025",
      "meter": "وافر",
      "verses": [
        {
          "verse_index": 0,
          "text": "غراس كالفتائن مغرضاتٌ  على آبارها أبداً عُطون"
        }
      ]
    }
  ]
}